{"id": 101618, "url": "https://www.liputan6.com/news/read/101618/warga-kapuas-menuntut-hak-ulayat", "clean_article": [["Liputan6", ".", "com", ",", "Kapuas", ":", "Ribuan", "warga", "sekitar", "Sungai", "Kapuas", "yang", "menggantungkan", "hidup", "dari", "menebang", "kayu", "berunjuk", "rasa", "ke", "Gedung", "DPRD", "Kabupaten", "Kapuas", ",", "Kalimantan", "Tengah", ",", "baru-baru", "ini", "."], ["Dalam", "aksinya", ",", "mereka", "meminta", "Pemerintah", "Kabupaten", "Kapuas", "tak", "hanya", "menertibkan", "praktik", "pembalakan", "ilegal", "."], ["Akan", "tetapi", ",", "Pemkab", "Kapuas", "mempunyai", "kebijakan", "untuk", "mencarikan", "jalan", "keluar", "dan", "menyediakan", "lapangan", "pekerjaan", "bagi", "warga", "untuk", "bertahan", "hidup", "."], ["Demonstrasi", "diawali", "dengan", "aksi", "jalan", "kaki", "menuju", "Kantor", "DPRD", "Kapuas", "."], ["Sepanjang", "jalan", ",", "secara", "bergantian", "mereka", "berorasi", "meminta", "Pemkab", "Kapuas", "lebih", "memperhatikan", "kesejahteraan", "warga", "."], ["Setiba", "di", "Gedung", "DPRD", "Kapuas", ",", "pengunjuk", "rasa", "sempat", "terlibat", "aksi", "saling", "dorong", "dengan", "polisi", "yang", "berjaga", "di", "depan", "Kantor", "DPRD", "."], ["Suasana", "mereda", "setelah", "salah", "satu", "pimpinan", "DPRD", "Kabupaten", "Kapuas", "menerima", "tujuh", "wakil", "pengunjuk", "rasa", "."], ["Dalam", "pertemuannya", ",", "mereka", "menuntut", "para", "anggota", "DPRD", "Kabupaten", "Kapuas", "agar", "berpihak", "kepada", "kepentingan", "rakyat", "sesuai", "dengan", "wilayah", "pemilihannya", "masing-masing", "."], ["Mereka", "berharap", "para", "anggota", "DPRD", "berinisiatif", "membuat", "peraturan", "daerah", "tentang", "penggunaan", "hak", "ulayat", "atau", "hak", "adat", "yang", "melibatkan", "demang", "atau", "kepala", "daerah", "di", "Kabupaten", "Kapuas", ".", "(", "ZIZ/Ririen", "Binti", ")", "."]], "clean_summary": [["Ribuan", "warga", "sekitar", "Sungai", "Kapuas", "yang", "menggantungkan", "hidup", "dari", "menebang", "kayu", "menuntut", "hak", "ulayat", "kepada", "anggota", "DPRD", "Kabupaten", "Kapuas", ",", "Kalteng", "."], ["Mereka", "meminta", "anggota", "Dewan", "tak", "hanya", "menertibkan", "pembalakan", "liar", "."]], "extractive_summary": [0, 1]}