{"id": 106841, "url": "https://www.liputan6.com/news/read/106841/keluarga-korban-penggusuran-tidur-tanpa-atap", "clean_article": [["Liputan6", ".", "com", ",", "Makassar", ":", "Derita", "keluarga", "Daeng", "Manda", "seakan", "tak", "ada", "habisnya", "."], ["Setelah", "lama", "tidak", "bekerja", ",", "keluarga", "yang", "tinggal", "di", "Jalan", "Daeng", "Tata", "I", "Makassar", ",", "Sulawesi", "Selatan", ",", "ini", "menjadi", "korban", "penggusuran", "Pemerintah", "Kota", "Makassar", ",", "Senin", "(", "8/8", ")", "siang", "."], ["Parahnya", "lagi", ",", "tempat", "yang", "akan", "dijadikan", "jalan", "umum", "itu", "mendapat", "ganti", "rugi", "yang", "tidak", "layak", "."], ["Pascapenggusuran", ",", "keluarga", "Daeng", "Manda", "tinggal", "dan", "tidur", "hanya", "bertabir", "kelambu", "."], ["Mereka", "akan", "mengungsi", "ke", "tempat", "lain", "jika", "turun", "hujan", "."], ["Situasi", "ini", "membuat", "Ardi", ",", "anak", "kedelapan", "dari", "sembilan", "bersaudara", "Daeng", "Manda", "terpaksa", "berhenti", "sekolah", "."], ["Sementara", ",", "anak", "Daeng", "Manda", "yang", "lain", "harus", "mencari", "penghidupan", "sendiri", "."], ["Saat", "ini", ",", "keluarga", "malang", "tersebut", "bergantung", "pemberian", "orang-orang", "yang", "menaruh", "kasihan", "kepada", "mereka", "."], ["Sebagai", "ganti", "rugi", "tanah", "beserta", "bangunan", "seluas", "100", "meter", "persegi", ",", "Pemkot", "Makassar", "telah", "memberikan", "tanah", "seluas", "108", "meter", "di", "Desa", "Taeng", ",", "Kabupaten", "Gowa", "."], ["Namun", ",", "pihak", "keluarga", "Daeng", "Manda", "tidak", "setuju", "dengan", "tanah", "pengganti", "yang", "diberikan", "pemerintah", "setempat", "."], ["Mereka", "menilai", ",", "ganti", "rugi", "itu", "tidak", "setara", "dengan", "tanah", "mereka", "yang", "terletak", "di", "Kota", "Makassar", "[", "baca", ":", "Penggusuran", "di", "Jalan", "Daeng", "Tata", "Makassar", "Tegang", "]", ".", "(", "DNP/Muhammad", "Takbir", "dan", "Sahran", "Amir", ")", "."]], "clean_summary": [["Setelah", "digusur", "Pemerintah", "Kota", "Makasar", ",", "Sulawesi", "Selatan", ",", "keluarga", "Daeng", "Manda", "di", "Jalan", "Daeng", "Tata", "I", "Makassar", ",", "tidur", "di", "sekitar", "puing", "rumah", "."], ["Bekas", "rumah", "warga", "ini", "akan", "dijadikan", "jalan", "umum", "."]], "extractive_summary": [1, 3]}