{"id": 109310, "url": "https://www.liputan6.com/news/read/109310/pemerintah-yakin-stok-barang-aman", "clean_article": [["Liputan6", ".", "com", ",", "Jakarta", ":", "Pemerintah", "menjamin", "stok", "bahan", "kebutuhan", "pokok", "menyusul", "rencana", "kenaikan", "harga", "bahan", "bakar", "minyak", "awal", "Oktober", "2005", "."], ["Pemerintah", ",", "dalam", "waktu", "dekat", ",", "berencana", "mengimpor", "beras", "mulai", "awal", "bulan", "depan", "."], ["PT", "Perkebunan", "Nusantara", "pun", "akan", "menggiatkan", "operasi", "pasar", "khusus", "komoditi", "gula", "."], ["Demikian", "diungkapkan", "Menteri", "Perdagangan", "Mari", "Elka", "Pangestu", "di", "Jakarta", ",", "baru-baru", "ini", "[", "baca", ":", "Harga", "BBM", "Akan", "Naik", "]", ".", "."], ["Mari", "tak", "bisa", "menampik", ",", "pasar", "pasti", "bergeliat", "menyusul", "rencana", "pemerintah", "mendongkrak", "harga", "BBM", "sampai", "50", "persen", "."], ["Ini", "seperti", "efek", "domino", "."], ["Apalagi", ",", "momennya", "pas", ":", "menjelang", "bulan", "Puasa", "dan", "Lebaran", "."], ["Untuk", "itu", ",", "tambah", "Mari", ",", "pemerintah", "akan", "berusaha", "sekuat", "tenaga", "meredam", "kemungkinan", "adanya", "gejolak", "harga", "."], ["Menteri", "Perdagangan", "memperkirakan", ",", "harga", "kebutuhan", "pokok", "akan", "naik", "lima", "hingga", "10", "persen", "."], ["Dia", "mengakui", ",", "dampak", "psikologis", "rencana", "kenaikan", "harga", "BBM", "jauh", "lebih", "besar", "dibanding", "pengaruh", "langsung", "harga", "baru", "bahan", "bakar", "minyak", "."], ["\"", "Untuk", "itu", ",", "pemerintah", "akan", "terus", "menjaga", "dan", "memantau", "aspek", "psikologis", "."], ["Menjamin", "ketersediaan", "barang", "cukup", ",", "\"", "ungkap", "Mari", ".", "(", "ICH/Winny", "Arnold", "dan", "Donni", "Indradi", ")", "."]], "clean_summary": [["Pasar", "pasti", "bergeliat", "menyusul", "rencana", "pemerintah", "mendongkrak", "harga", "bahan", "bakar", "minyak", "sampai", "50", "persen", ",", "apalagi", "momennya", "pas", ":", "menjelang", "bulan", "suci", "Ramadan", "dan", "Lebaran", "."], ["Pemerintah", "berencana", "mengimpor", "beras", "."]], "extractive_summary": [4, 6]}