{"id": 156985, "url": "https://www.liputan6.com/news/read/156985/tni-au-salurkan-bantuan-lewat-udara", "clean_article": [["Liputan6", ".", "com", ",", "Pekanbaru", ":", "TNI", "Angkatan", "Udara", "memberikan", "bantuan", "kepada", "korban", "banjir", "di", "Pekanbaru", ",", "Kepulauan", "Riau", "dengan", "melemparkan", "kotak", "mi", "instan", "dari", "helikopter", "agar", "distribusi", "merata", "."], ["Selama", "ini", "bantuan", "sering", "tak", "sampai", "terutama", "ke", "warga", "yang", "bertahan", "di", "rumah", "."], ["Banjir", "yang", "merendam", "sembilan", "dari", "sebelas", "wilayah", "kabupaten", "dan", "kota", "di", "Pekanbaru", "belum", "surut", "hingga", "Kamis", "(", "27/3", ")", "petang", "."], ["Sejumlah", "ruas", "jalan", "di", "permukiman", "tak", "bisa", "lagi", "dilewati", "."], ["Sebagian", "rumah", "ditinggal", "mengungsi", "para", "penghuninya", "."], ["Diperkirakan", "11", "ribu", "kepala", "keluarga", "mengungsi", "karena", "makin", "tingginya", "luapan", "air", "Sungai", "Siak", "."], ["Luapan", "Sungai", "Siak", "juga", "meredam", "Pasar", "Bawah", "Pekanbaru", "."], ["Kawasan", "yang", "dikenal", "sebagai", "pasar", "wisata", "ini", "lumpuh", "total", "."], ["Ratusan", "pedagang", "pakaian", "dan", "perlengkapan", "rumah", "tangga", "mengungsikan", "barang", "dagangan", "mereka", "yang", "sudah", "basah", "karena", "terendam", "[", "baca", ":", "Korban", "Banjir", "Rumbai", "Kembali", "Mengungsi", "]", "."], ["Tahun", "ini", "banjir", "musiman", "di", "Riau", "lebih", "parah", "karena", "lima", "sungai", "utama", "meluap", "hampir", "bersamaan", "."], ["Selain", "Pekanbaru", ",", "banjir", "menimpa", "delapan", "kabupaten", "di", "propinsi", "tersebut", "."], ["Air", "Sungai", "Siak", "yang", "berhulu", "di", "Tapung", ",", "Kabupaten", "Bengkalis", "setiap", "sore", "terus", "meninggi", "seiring", "naiknya", "arus", "pasang", "."], ["Sementara", "banjir", "di", "Martapura", ",", "Kabupaten", "Banjar", ",", "Kalimantan", "Selatan", "sudah", "memasuki", "hari", "keempat", "."], ["Sekalipun", "debet", "air", "mengalami", "penurunan", ",", "kondisi", "permukiman", "di", "sejumlah", "kecamatan", "dan", "desa", "masih", "tergenang", "."], ["Akibatnya", "aktivitas", "warga", "terhambat", "dan", "sejumlah", "sekolah", "terpaksa", "diliburkan", "."], ["Daerah", "terparah", "dan", "masih", "cukup", "dalam", "terendam", "air", "adalah", "Desa", "Munggu", "Raya", "(", "Kecamatan", "Astambul", ")", ",", "Desa", "Tanah", "Abang", "dan", "Desa", "Tambak", "Baru", "(", "Kecamatan", "Martapura", "Kota", ")", "."], ["Ketinggian", "air", "di", "wilayah", "ini", "mencapai", "satu", "meter", "."], ["Banjir", "menggenangi", "sebagian", "jalan", "raya", "di", "kawasan", "tersebut", "."], ["Banjir", "juga", "menerjang", "daerah", "Topoyo", ",", "Sulawesi", "Barat", "."], ["Selama", "dua", "hari", "puluhan", "anak-anak", "hidup", "dengan", "kondisi", "seadanya", "dan", "kini", "mereka", "terancam", "terserang", "berbagai", "penyakit", "seperti", "malaria", "dan", "muntaber", "."], ["Banjir", "diakibatkan", "meluapnya", "Sungai", "Topoyo", "."], ["Banjir", "telah", "memutuskan", "jalan", "yang", "menghubungkan", "Topoyo", "dan", "Karossa", ".", "(", "JUM/Tim", "Liputan", "6", "SCTV", ")", "."]], "clean_summary": [["TNI", "AU", "memberikan", "bantuan", "kepada", "korban", "banjir", "di", "Pekanbaru", ",", "Riau", "dengan", "melemparkan", "kotak", "mi", "instan", "dari", "helikopter", "agar", "distribusi", "merata", "."], ["Selama", "ini", "bantuan", "sering", "tak", "sampai", "terutama", "ke", "warga", "yang", "bertahan", "di", "rumah", "."]], "extractive_summary": [0, 1]}