{"id": 205758, "url": "https://www.liputan6.com/news/read/205758/bardsley-betah-di-villa", "clean_article": [["Bek", "kanan", "Manchester", "United", ",", "Phil", "Bardsley", "nampaknya", "telah", "menemukan", "klub", "baru", "untuk", "menambatkan", "karirnya", "yang", "masih", "panjang", "terbentang", "di", "depan", "."], ["Pemain", "berusia", "21", "tahun", "tersebut", "jengah", "bermain", "untuk", "The", "Red", "Devils", "yang", "hanya", "menjadikannya", "sebagai", "pemain", "pelapis", "yang", "belum", "tentu", "mendapat", "tempat", "di", "tim", "inti", "."], ["Paruh", "pertama", "musim", "ini", ",", "Bardsley", "dipinjamkan", "ke", "Rangers", "."], ["Balik", "ke", "Manchester", "ia", "lantas", "kembali", "dipinjamkan", ",", "kali", "ini", "ke", "Aston", "Villa", "yang", "tengah", "melakukan", "pembenahan", "baik", "dari", "segi", "teknis", "maupun", "non-teknis", "."], ["Bardsley", "yakin", "Villa", "sedang", "menapaki", "jalur", "yang", "tepat", "dibawah", "manajer", "Martin", "O", "Neill", "setelah", "dalam", "beberapa", "tahun", "terakhir", "terombang-ambing", "tanpa", "arah", ".", "Bardsley", "menunjuk", "kepada", "langkah", "O", "Neill", "di", "bursa", "transfer", "Januari", "ini", "dengan", "memboyong", "dua", "striker", "impresif", ",", "John", "Carew", "dan", "Ashley", "Young", "."], ["Sementara", "untuk", "urusan", "non-teknis", "Villa", "akan", "membangun", "pusat", "latihan", "baru", "yang", "menghabiskan", "dana", "sebesar", "8", "juta", "pound", "untuk", "menggantikan", "pusat", "latihan", "sebelumnya", ",", "Bodymoor", "Heath", "."], ["Dikutip", "dari", "PA", "Sport", ",", "Bardsley", "berkata", ":", "\u201c", "Menurut", "hemat", "saya", "Villa", "telah", "menapaki", "langkahnya", "dengan", "tepat", "."], ["Sejujurnya", "saya", "yakin", "kami", "berada", "di", "jalur", "yang", "benar", "."], ["Klub", "menapaki", "masa", "depan", "yang", "cerah", "dengan", "stadion", "yang", "terus", "mengalami", "pembenahan", ",", "pusat", "latihan", "yang", "sedang", "dibangun", "dan", "beberapa", "pemain", "yang", "direkrutnya", ".", "\u201d", "The", "Villans", "sukses", "mengakhiri", "rekor", "buruknya", "sebelas", "kali", "bermain", "tanpa", "satupun", "kemenangan", "di", "ajang", "Premiership", "setelah", "meraih", "kemenangan", "dari", "Watford", "akhir", "pekan", "lalu", "."], ["Sejatinya", "Villa", "mengawali", "musim", "ini", "dengan", "begitu", "cemerlang", "."], ["Sampai", "November", "tahun", "lalu", ",", "The", "Villans", "mampu", "bertengger", "di", "peringkat", "ketiga", "dan", "Bardsley", "tidak", "meragukan", "jika", "timnya", "kembali", "merangkak", "naik", "di", "klasemen", ".", "\u201c", "Ketika", "saya", "melihat", "kualitas", "yang", "dimiliki", "skuad", "kami", ",", "saya", "dapat", "melihat", "dimana", "seharusnya", "kami", "berada", "."], ["Kami", "seharusnya", "berada", "pada", "peringkat", "yang", "jauh", "lebih", "baik", "dari", "saat", "ini", ".", "\u201d", "Dengan", "mengacu", "pada", "pencapaian", "Manchester", "City", "yang", "mampu", "memperbaiki", "peringkatnya", "di", "klasemen", "setelah", "sebelumnya", "menuai", "hasil", "buruk", "di", "awal", "musim", ",", "\u201c", "Saya", "yakin", "kami", "akan", "mampu", "meraih", "hasil", "yang", "memuaskan", "untuk", "merangkak", "naik", "di", "klasemen", "."], ["Saya", "rasa", "kami", "mampu", "meraih", "satu", "tempat", "di", "kejuaraan", "Eropa", "dan", "tidak", "tertutup", "kemungkinan", "musim", "ini", "juga", ",", "\u201d", "tukasnya", "."], ["Dengan", "kontrak", "peminjaman", "yang", "telah", "disepakati", "bersama", "antara", "MU", "dan", "Villa", ",", "Bardsley", "akan", "dipinjam", "sampai", "akhir", "musim", "."], ["Tapi", "ia", "berharap", ",", "\u201c", "Jika", "masa", "depan", "karir", "saya", "diputuskan", "bersama", "Aston", "Villa", ",", "saya", "akan", "merasa", "bahagia", "sekali", "."], ["Itu", "semua", "tergantung", "kepada", "manajer", "(", "Martin", "O", "Neill", ")", "apakah", "ia", "menginginkan", "saya", "untuk", "tetap", "di", "sini", "atau", "tidak", "."], ["Saya", "akan", "melihat", "kemungkinan", "itu", "secara", "optimis", ".", "\u201d", "."]], "clean_summary": [["Baru", "saja", "bergabung", "dengan", "Aston", "Villa", "sebagai", "pemain", "pinjaman", ",", "Phil", "Barsley", "tidak", "akan", "menolak", "jika", "klub", "tersebut", "mau", "mengikatnya", "secara", "permanen", "."], ["\u201c", "Jika", "karir", "saya", "diputuskan", "untuk", "Villa", "maka", "saya", "akan", "merasa", "bahagia", ",", "\u201d", "katanya", "."]], "extractive_summary": [14, 16]}