{"id": 206609, "url": "https://www.liputan6.com/news/read/206609/struktur-baru-di-stamford-bridge", "clean_article": [["Para", "petinggi", "klub", "Chelsea", "sedang", "mempertimbangkan", "alternatif", "baru", "dalam", "soal", "kepelatihan", "klub", "di", "musim", "depan", "."], ["Dalam", "skema", "(", "radikal", ")", "baru", "itu", "tampak", "jelas", "tidak", "ada", "tempat", "lagi", "bagi", "Jose", "Mourinho", "yang", "kini", "berfungsi", "sebagai", "manajer", "tim", "."], ["Struktur", "baru", "tersebut", "diyakini", "untuk", "mengatasi", "gap", "yang", "terjadi", "antara", "seorang", "manajer", "dengan", "pemilik", "klub", ",", "Roman", "Abramovich", ",", "seperti", "halnya", "yang", "kini", "terjadi", "di", "Stamford", "Bridge", ".", "Dikatakan", "tidak", "ada", "tempat", "lagi", "bagi", "Mourinho", "didasarkan", "atas", "dua", "posisi", "yang", "bakal", "diterapkan", "Abramovich", "dalam", "manajemen", "tim", "di", "musim", "depan", "."], ["Dua", "posisi", "dimaksud", "adalah", "seorang", "pelatih", "yang", "khusus", "menangani", "tim", "."], ["Sangat", "besar", "kemungkinan", ",", "untuk", "posisi", "ini", "Abramovich", "menginginkan", "seorang", "pelatih", "lokal", "atau", "dalam", "arti", "kata", "ia", "berasal", "dari", "Inggris", "."], ["Mourinho", "?"], ["Jelas", ",", "bukan", "toh", "!", "Nah", ",", "satu", "posisi", "lainnya", "yang", "boleh", "dibilang", "setingkat", "kedudukannya", "di", "atas", "pelatih", "tim", "tersebut", "adalah", "posisi", "pengatur", "atau", "pengawas", "pelatih", "."], ["Untuk", "tugas", "ini", ",", "seperti", "yang", "dilansir", "Independent", ",", "di", "mata", "Abramovich", "hanya", "terdapat", "satu", "sosok", "di", "muka", "bumi", "ini", "yang", "cocok", "dengan", "tugas", "seperti", "itu", ",", "yaitu", "Guus", "Hiddink", ".", "Proposal", "dua", "pelatih", "itu", "kini", "sedang", "digodok", "."], ["Tanda-tandanya", "semakin", "terlihat", "seusai", "pertandingan", "Chelsea", "vs", "Watford", "di", "Vicarage", "Road", "Stadium", ",", "Sabtu", "lalu", "."], ["Abramovich", "kembali", "berbuat", "ulah", "tidak", "mau", "mendatangi", "kamar", "ganti", "pemain", "alias", "masih", "enggan", "bertemu", "dengan", "Mourinho", "."], ["Yang", "nongol", "menyambangi", "John", "Terry", "dkk", "adalah", "tiga", "pejabat", "elite", "klub", ",", "Chairman", "Bruce", "Buck", ",", "Chief", "Executive", "Peter", "Kenyon", "dan", "Direktur", "Eugene", "Tenenbaum", ",", "salah", "satu", "orang", "kepercayaan", "Abramovich", ".", "Mendapat", "perlakuan", "seperti", "itu", "Mourinho", "tak", "mau", "terpancing", "."], ["\u201c", "Bagi", "saya", ",", "itu", "(", "tindakan", "Abramovich", "yang", "tidak", "mendatangi", "kamar", "ganti", "pemain", ")", "bukan", "masalah", "besar", "."], ["Tampaknya", ",", "ia", "cukup", "gembira", "(", "dengan", "kemenangan", "Chelsea", ")", ",", "sama", "seperti", "apa", "yang", "dirasakan", "tim", "."], ["Sebab", ",", "jika", "kami", "kehilangan", "dua", "poin", "berarti", "kami", "telah", "kehilangan", "gelar", "premiership", "."], ["Jadi", ",", "gol", "(", "Salomon", ")", "Kalou", "benar-benar", "pantas", "kami", "rayakan", ",", "\u201d", "ujar", "Mourinho", ".", "Masuknya", "Hiddink", "akan", "menambah", "kental", "nuansa", "Belandanisasi", "di", "Stamford", "Bridge", "."], ["Saat", "ini", "telah", "ada", "dua", "sosok", "Belanda", "di", "kubu", "The", "Blues", ",", "Frank", "Arnesen", ",", "Direktur", "Pengembangan", "Sepakbola", "sekaligus", "Ketua", "Tim", "Pemandu", "Bakat", "dan", "penasihatnya", ",", "Piet", "de", "Visser", "."], ["Struktur", "dual", "role", "itu", "juga", "tampaknya", "cocok", "bagi", "Hiddink", "yang", "kini", "menjabat", "pelatih", "Timnas", "Rusia", ":", "tim", "saingan", "Inggris", "di", "kualifikasi", "Euro", "2008", "."]], "clean_summary": [["Spekulasi", "model", "baru", "dalam", "tubuh", "Chelsea", "semakin", "kencang", "terdengar", "."], ["Musim", "depan", "klub", "akan", "ditangani", "dua", "figur", ":", "satu", "pelatih", "lokal", "(", "Inggris", ")", "yang", "menangani", "langsung", "tim", "dan", "satu", "lagi", "berfungsi", "sebagai", "pengatur", ":", "posisi", "yang", "bakal", "diisi", "Guus", "Hiddink", "."]], "extractive_summary": [0, 3, 1]}