{"id": 243604, "url": "https://www.liputan6.com/news/read/243604/kpu--separuh-biaya-pelantikan-bisa-dihemat", "clean_article": [["Liputan6", ".", "com", ",", "Banjarmasin", ":", "Ketua", "Komisi", "Pemilihan", "Umum", "Abdul", "Hafiz", "Anshary", "mengatakan", "pihaknya", "akan", "menghemat", "biaya", "pelantikan", "anggota", "DPR", "dan", "DPD", "pada", "1", "Oktober", "mendatang", "."], ["\"", "Saya", "berharap", "penghematan", "bisa", "dilakukan", "hingga", "50", "persen", "dari", "pagu", "anggaran", "yang", "ditetapkan", "Rp", "11", "miliar", ",", "\"", "kata", "Hafiz", "usai", "pelantikan", "anggota", "DPRD", "Kalimantan", "Selatan", "di", "Banjarmasin", ",", "Rabu", "(", "9/9", ")", "seperti", "dikutip", "ANTARA", "."], ["Menurut", "Hafiz", "Anshary", ",", "anggaran", "Rp", "11", "miliar", "yang", "diambilkan", "dari", "daftar", "isian", "proyek", "anggaran", "hanya", "pagu", "biaya", "pelantikan", ",", "tapi", "realisasinya", "bisa", "jauh", "di", "bawah", "angka", "tersebut", "."], ["Hafiz", "mencontohkan", "pengadaan", "kertas", "suara", "pada", "pemilu", "lalu", "dianggarkan", "Rp", "1", ",", "8", "triliun", "namun", "hanya", "terpakai", "Rp", "600", "miliar", "sehingga", "bisa", "dilakukan", "penghematan", "Rp", "1", ",", "2", "triliun", "."], ["Begitu", "juga", "dengan", "biaya", "pelantikan", "wakil", "rakyat", "diharapkan", "realisasinya", "jauh", "di", "bawah", "anggaran", "yang", "ditetapkan", "."], ["Beberapa", "komponen", "yang", "bisa", "dilakukan", "penghematan", "di", "antaranya", "konsumsi", ",", "pencetakan", "buku", ",", "dan", "beberapa", "kelengkapan", "pribadi", "anggota", "DPR", "lainnya", "."], ["\"", "Seperti", "baju", ",", "kita", "tidak", "belikan", ",", "karena", "orangnya", "terlalu", "banyak", "mencapai", "692", "orang", ",", "\"", "kata", "dia", "."], ["Komponen", "yang", "tidak", "bisa", "dihemat", "di", "antaranya", "transportasi", "karena", "disesuaikan", "dengan", "harga", "tiket", "perjalanan", "dari", "daerah", "asal", "menuju", "Jakarta", "."], ["Sementara", "biaya", "untuk", "pelantikan", "anggota", "DPRD", "baru", "ditanggung", "masing-masing", "DPRD", "daerah", "penyelenggara", "."], ["Hafiz", "mengatakan", "pelantikan", "anggota", "DPR", "dan", "DPD", "pada", "Oktober", "akan", "dijaga", "ketat", "oleh", "6", ".", "000", "personel", "kepolisian", ".", "(", "JUM/AND", ")", "."]], "clean_summary": [["KPU", "akan", "menghemat", "biaya", "pelantikan", "wakil", "rakyat", "pada", "1", "Oktober", "mendatang", "."], ["Ketua", "KPU", "Abdul", "Hafiz", "Anshary", "berharap", "penghematan", "bisa", "dilakukan", "hingga", "50", "persen", "dari", "pagu", "anggaran", "yang", "ditetapkan", "Rp", "11", "miliar", "."]], "extractive_summary": [0, 1]}