{"id": 257369, "url": "https://www.liputan6.com/news/read/257369/mesin-blower-meledak--dua-pekerja-luka-bakar", "clean_article": [["Liputan6", ".", "com", ",", "Temanggung", ":", "Dua", "orang", "pekerja", "mengalami", "luka", "bakar", "serius", "akibat", "terkena", "ledakan", "mesin", "blower", "di", "pabrik", "kayu", "lapis", "CV", "Cipta", "Usaha", "Mandiri", ",", "yang", "berlokasi", "di", "Dusun", "Klimbungan", ",", "Desa", "Medari", ",", "Kecamatan", "Ngadirejo", ",", "Kabupaten", "Temanggung", ",", "Senin", "(", "4/1", ")", "pagi", "."], ["Korban", "bernama", "Joko", "kini", "dirawat", "di", "Rumah", "Sakit", "Sardjito", "Yogyakarta", ",", "akibat", "luka", "bakar", "yang", "serius", "."], ["Sedangkan", "korban", "lain", "bernama", "Rodin", "masih", "dirawat", "di", "Rumah", "Sakit", "Kristen", ",", "Ngesti", "Waluyo", ",", "Parakan", "."], ["Menurut", "Rodin", ",", "peristiwa", "ini", "berawal", "dari", "terbakarnya", "mesin", "blower", "."], ["Ketika", "ia", "bersama", "Joko", "hendak", "menyalakan", "hindran", "untuk", "memadamkan", "api", ",", "tiba-tiba", "blower", "itu", "meledak", "."], ["Sejauh", "ini", ",", "pihak", "CV", "Cipta", "Usaha", "Mandiri", "belum", "mau", "memberikan", "komentar", "."], ["Dari", "informasi", "yang", "dihimpun", "SCTV", ",", "ledakan", "serupa", "sebelumnya", "pernah", "dua", "kali", "terjadi", "."], ["(", "MLA", ")", "."]], "clean_summary": [["Dua", "pekerja", "mengalami", "luka", "bakar", "serius", "akibat", "terkena", "ledakan", "mesin", "blower", "di", "sebuah", "pabrik", "kayu", "lapis", "di", "Temanggung", ",", "Senin", "pagi", "."]], "extractive_summary": [0, 7]}