{"id": 258029, "url": "https://www.liputan6.com/news/read/258029/rambut-asli-angelina-jolie-pirang", "clean_article": [["Liputan6", ".", "com", ",", "Amerika", ":", "Artis", "seksi", "berusia", "34", "tahun", ",", "Angelina", "Jolie", ",", "ternyata", "memiliki", "rambut", "asli", "berwarna", "pirang", ",", "seperti", "dilansir", "ContactMusic", ",", "Jumat", "(", "8/1", ")", "."], ["Jolie", "mengatakan", "ibunya", ",", "mendiang", "Marcheline", "Bertrand", ",", "mulai", "mengubah", "warna", "rambut", "anaknya", ",", "karena", "ia", "tidak", "suka", "dengan", "warna", "rambut", "asli", "Jolie", "tersebut", "."], ["Istri", "Brad", "Pitt", "ini", "mengatakan", "kepada", "majalah", "Jerman", ",", "Das", "Neue", ",", "\"", "Warna", "asli", "rambut", "saya", "adalah", "pirang", "gelap", "."], ["Tetapi", "ketika", "saya", "berusia", "empat", "atau", "lima", "tahun", ",", "ibu", "mengecat", "rambut", "saya", "menjadi", "cokelat", "gelap", "."], ["Ia", "menginginkan", "untuk", "tetap", "seperti", "itu", ",", "dan", "hingga", "sekarang", "saya", "terus", "mengecat", "rambut", "ini", ".", "\"", "(", "YUS", ")", "."]], "clean_summary": [["Artis", "seksi", "Angelina", "Jolie", "mengubah", "warna", "rambutnya", "sejak", "berusia", "empat", "tahun", "."], ["Aslinya", "rambut", "Jolie", "berwarna", "pirang", "."]], "extractive_summary": [0, 1]}