{"id": 286494, "url": "https://www.liputan6.com/news/read/286494/puluhan-ribu-tabung-gas-ditemukan-rusak", "clean_article": [["Liputan6", ".", "com", ",", "Jombang", ":", "Tim", "gabungan", "dari", "Dinas", "Perindustrian", "Jombang", "dan", "petugas", "Kepolisian", "Resor", "Jombang", ",", "Jawa", "Timur", ",", "menggelar", "sidak", "ke", "stasiun", "pengisian", "elpiji", ",", "Kamis", "(", "15/7", ")", "."], ["Di", "tempat", "itu", ",", "petugas", "menemukan", "puluhan", "ribu", "tabung", "gas", "ukuran", "tiga", "kilogram", "yang", "sudah", "rusak", "."], ["Dari", "temuan", "ini", ",", "tim", "gabungan", "meminta", "pemilik", "SPBE", "agar", "waspada", "karena", "masih", "banyak", "tabung", "gas", "tidak", "berlabel", "SNI", "beredar", "dipasaran", "."], ["Tim", "rencananya", "akan", "terus", "memantau", "peredaran", "tabung", "gas", "untuk", "meminimalisir", "kemungkinan", "terjadinya", "ledakan", "yang", "menewaskan", "korban", "jiwa", "."], ["Sementara", "itu", ",", "tabung", "gas", "ukuran", "tiga", "kilogram", "bermasalah", "juga", "ditemukan", "di", "sejumlah", "distributor", "di", "Sumedang", ",", "Jawa", "Barat", "."], ["Bahkan", "saat", "dites", "kelayakannya", "sejumlah", "tabung", "gas", "yang", "diproduksi", "tahun", "2007/2008", "dan", "tidak", "berlabel", "SNI", "mengeluarkan", "gelembung", "udara", "saat", "di", "masukkan", "ke", "dalam", "air", "[", "baca", ":", "Tabung", "Gas", "Bocor", "Ditambal", "Sabun", "]", ".", "(", "IAN", ")", "."]], "clean_summary": [["Guna", "mencegah", "jatuhnya", "korban", "jiwa", "akibat", "ledakan", "elpiij", ",", "tim", "gabungan", "Dinas", "Perindustrian", "Kabupaten", "Jombang", ",", "Jatim", ",", "dan", "polisi", "menggelar", "sidak", "ke", "stasiun", "pengisian", "gas", "."]], "extractive_summary": [0, 3]}