{"id": 294065, "url": "https://www.liputan6.com/news/read/294065/banjir-landa-nikaragua--37-nyawa-melayang", "clean_article": [["Liputan6", ".", "com", ",", "Managua", ":", "Banjir", "menerjang", "Nikaragua", ",", "Senin", "(", "30/8", ")", "silam", ",", "sehingga", "menewaskan", "37", "orang", "."], ["Diperkirakan", ",", "korban", "meninggal", "saat", "berupaya", "menyeberangi", "banjir", "."], ["Namun", ",", "korban", "terseret", "aliran", "arus", "yang", "deras", "."], ["Selain", "itu", "debit", "air", "yang", "tinggi", "juga", "menyebabkan", "korban", "tidak", "dapat", "diselamatkan", "lagi", "."], ["Salah", "satu", "pejabat", "pemerintah", "mengatakan", ",", "saat", "ini", "perahu", "karet", "dan", "cadangan", "gandum", "telah", "dikirim", "ke", "daerah-daerah", "yang", "terkena", "bencana", "paling", "parah", "."], ["Apalagi", ",", "sejak", "Mei", "silam", ",", "banjir", "melanda", "57", "kota", "di", "10", "provinsi", "di", "negara", "yang", "berada", "di", "Amerika", "Tengah", "ini", "."], ["Kini", ",", "sekitar", "32", "ribu", "orang", "mengungsi", "ke", "tempat", "yang", "lebih", "aman", "."], ["Banjir", "yang", "disebabkan", "oleh", "hujan", "deras", "ini", "juga", "mengakibatkan", "puluhan", "rumah", "rusak", "parah", "."], ["Hujan", "deras", "dan", "badai", "petir", "juga", "menyebabkan", "listrik", "padam", "di", "beberapa", "daerah", ".", "(", "ANS/Xinhua", ")", "."]], "clean_summary": [["Banjir", "yang", "menerjang", "Nikaragua", ",", "mengakibatkan", "37", "orang", "tewas", "dan", "puluhan", "ribu", "lainnya", "harus", "dievakuasi", "."]], "extractive_summary": [0, 7]}