{"id": 298522, "url": "https://www.liputan6.com/news/read/298522/dilarang-meliput--puluhan-wartawan-protes", "clean_article": [["Liputan6", ".", "com", ",", "Gresik", ":", "Sekitar", "20", "wartawan", "dari", "media", "cetak", "maupun", "elektronik", "meletakkan", "kartu", "pengenal", "peliputan", "dari", "sekretariat", "Kabupatem", "Gresik", ",", "Jawa", "Timur", ",", "Senin", "(", "27/9", ")", "."], ["Kartu", "itu", "diletakkan", "di", "lantai", "pintu", "masuk", "ruangan", "tempat", "prosesi", "pelantikan", "bupati", "dan", "wakil", "bupati", "Gresik", "terpilih", "periode", "2010-2015", "."], ["Tak", "hanya", "itu", ",", "mereka", "juga", "meletakkan", "kamera", "sebagai", "bentuk", "protes", "."], ["Aksi", "ini", "dilakukan", "setelah", "para", "wartawan", "tidak", "boleh", "memasuki", "ruang", "penatikan", "meski", "sudah", "menunjukkan", "kartu", "tanda", "pengenal", "tersebut", "."], ["Upaya", "lobi", "yang", "dilakukan", "tak", "berhasil", "sehingga", "akhirnya", "para", "wartawan", "meninggalkan", "lokasi", "pelantikan", "."], ["Acara", "pelantikan", "Bupati", "Sabari", "Halim", "dan", "Wakil", "Bupati", "Muhamad", "Qosim", "ini", "dijaga", "cukup", "ketat", "."], ["Sedikitnya", "800", "personel", "gabungan", "dikerahkan", "untuk", "menjaga", "pelantikan", "ini", ".", "(", "BOG", ")", "."]], "clean_summary": [["Dilarang", "meliput", "pelatikan", "bupati", "dan", "wakil", "bupati", "Gresik", "terpilih", ",", "puluhan", "wartawan", "protes", "."], ["Mereka", "meletakkan", "kartu", "pengenal", "dan", "kamera", "sebagai", "bentuk", "protes", "."]], "extractive_summary": [1, 2]}