{"id": 299277, "url": "https://www.liputan6.com/news/read/299277/sofyan-usman-mengaku-tak-kenal-nunun", "clean_article": [["Liputan6", ".", "com", ",", "Jakarta", ":", "Sofyan", "Usman", ",", "tersangka", "kasus", "suap", "pemilihan", "Deputi", "Gubernur", "Senior", "Bank", "Indonesia", "(", "BI", ")", "Miranda", "Gultom", ",", "didampingi", "kuasa", "hukumnya", "menjalani", "pemeriksaan", "di", "Komisi", "Pemberantasan", "Korupsi", "(", "KPK", ")", ",", "Jumat", "(", "1/10", ")", "."], ["Politisi", "Partai", "Persatuan", "Pembangunan", "itu", "dicecar", "sebanyak", "delapan", "pertanyaan", "oleh", "penyidik", "KPK", "[", "baca", ":", "KPK", "Periksa", "Sofyan", "Usman", "dan", "Daniel", "Tanjung", "]", "."], ["Dalam", "pemeriksaan", "Sofyan", "berkelit", "dirinya", "tidak", "mengenal", "Ari", "Malangyudo", "ataupun", "Nunun", "Nurbaeti", "."], ["Bahkan", "Sofyan", "mengaku", "tidak", "tahu", "menahu", "perihal", "pemberian", "cek", "perjalanan", "itu", "."], ["Kemarin", "KPK", "juga", "memeriksa", "tersangka", "Daniel", "Tanjung", "dalam", "kasus", "yang", "sama", "."], ["Sebelumnya", "anggota", "DPR", "dari", "Fraksi", "PDI", "Perjuangan", "Tjahyo", "Kumolo", "dan", "Panda", "Nababan", "telah", "pula", "diperiksa", "KPK", "."], ["Kasus", "cek", "perjalanan", "Miranda", "Gultom", "menyeret", "hampir", "seluruh", "anggota", "Komisi", "Keuangan", "dan", "Perbankan", "DPR", "saat", "itu", "."], ["Sampai", "saat", "ini", "sebanyak", "26", "tersangka", "sudah", "ditetapkan", "termasuk", "mantan", "Menteri", "Negara", "Perencanaan", "dan", "Pembangunan", "Nasional", "Paskah", "Suzetta", ".", "(", "IAN", ")", "."]], "clean_summary": [["KPK", "terus", "melanjutkan", "pemeriksaan", "tersangka", "kasus", "dugaan", "suap", "pemilihan", "Deputi", "Gubernur", "Senior", "BI", "Miranda", "Gultom", "."], ["Sofyan", "Usman", ",", "politisi", "dari", "PPP", ",", "mengaku", "tidak", "tahu", "menahu", "perihal", "pemberian", "cek", "perjalanan", "itu", "."]], "extractive_summary": [0, 3]}