{"id": 39140, "url": "https://www.liputan6.com/news/read/39140/debit-air-waduk-gajah-mungkur-merosot", "clean_article": [["Liputan6", ".", "com", ",", "Wonogiri", ":", "Debit", "air", "di", "Waduk", "Gajah", "Mungkur", "Wonogiri", ",", "Jawa", "Tengah", ",", "menyusut", "drastis", "dalam", "sebulan", "terakhir", "ini", "."], ["Hingga", "Senin", "(", "5/8", ")", ",", "penurunan", "debit", "air", "di", "waduk", "itu", "sudah", "mencapai", "empat", "meter", "."], ["Akibatnya", ",", "Pembangkit", "Litsrik", "Tenaga", "Air", "(", "PLTA", ")", "Gajah", "Mungkur", "hanya", "mengoperasikan", "satu", "turbin", "dari", "dua", "turbin", "yang", "ada", "."], ["Untuk", "mengaliri", "30", "ribu", "hektare", "lahan", "pertanian", "di", "Jawa", "Timur", "dan", "10", "ribu", "hektare", "di", "wilayah", "Sukoharjo", "dan", "Klaten", ",", "Jateng", ",", "dilakukan", "secara", "bergilir", "[", "baca", ":", "Kekeringan", "Parah", "Melanda", "Wonogiri", "]", "."], ["Menurut", "Staf", "Perencanaan", "Proyek", "Bengawan", "Solo", "Graita", "Sutadi", ",", "penyusutan", "juga", "terjadi", "di", "delapan", "bendungan", "yang", "berada", "dalam", "pantauannya", "."], ["Lima", "di", "antaranya", "Bendungan", "Cengklik", "Boyolali", ",", "Delingan", "Karanganyar", ",", "dan", "Gebyar", "di", "Sragen", "."], ["Begitu", "pula", "Bendungan", "Pondok", "dan", "Sangiran", "yang", "berada", "di", "Ngawi", ",", "Jatim", "."], ["Graita", "menjelaskan", ",", "untuk", "pelestarian", "Waduk", "Gajah", "Mungkur", ",", "pihaknya", "telah", "menerima", "dana", "hibah", "dari", "Japan", "International", "Convention", "Agency", "atau", "JICA", "sebesar", "Rp", "50", "miliar", "."], ["Seperti", "diketahui", ",", "penyusutan", "air", "akibat", "kemarau", "yang", "berkepanjangan", "juga", "melanda", "sejumlah", "waduk", "di", "Sumatra", "Barat", "."], ["Kondisi", "ini", "mengakibatkan", "PLTA", "Koto", "Panjang", ",", "yang", "memiliki", "tiga", "turbin", "berkekuatan", "38", "megawatt", "tak", "beroperasi", "maksimal", "."], ["Dari", "tiga", "turbin", "dengan", "kapasitas", "listrik", "114", "megawatt", ",", "hanya", "dua", "turbin", "yang", "beroperasi", "."], ["Itu", "pun", "dengan", "kapasitas", "listrik", "70", "megawatt", "[", "baca", ":", "Kemarau", "Mempengaruhi", "PLTA", "Koto", "Panjang", "]", ".", "(", "DEN/Solikun", ")", "."]], "clean_summary": [["Volume", "air", "di", "Waduk", "Gajah", "Mungkur", "Wonogiri", ",", "Jateng", ",", "menyusut", "drastis", "dalam", "sebulan", "terakhir", "."], ["Penyaluran", "air", "untuk", "puluhan", "ribu", "hektare", "lahan", "pertanian", "dibagikan", "bergilir", "."]], "extractive_summary": [0, 3]}