{"id": 40461, "url": "https://www.liputan6.com/news/read/40461/polisi-memeriksa-tiga-pelaku-pembakaran-bendera-malaysia", "clean_article": [["Liputan6", ".", "com", ",", "Jakarta", ":", "Kepolisian", "Resor", "Jakarta", "Selatan", ",", "Rabu", "(", "28/8", ")", ",", "memeriksa", "tiga", "pelaku", "pembakaran", "bendera", "Malaysia", "di", "Kedutaan", "Besar", "Malaysia", ",", "pekan", "silam", "."], ["Seorang", "di", "antaranya", "adalah", "Ketua", "Presidium", "Laskar", "Merah", "Putih", "Eddy", "Hartawan", "."], ["Ketiga", "orang", "itu", "diringkus", "di", "Perumahan", "Jati", "Unggul", "Bekasi", ",", "Jawa", "Barat", "."], ["Pemeriksaan", "yang", "dimulai", "pukul", "15", ".", "00", "WIB", "itu", "dilaksanakan", "tertutup", "."], ["Bahkan", ",", "polisi", "tak", "bersedia", "membeberkan", "hasil", "pemeriksaan", "."], ["Sekadar", "diketahui", ",", "pembakaran", "bendera", "Malaysia", "itu", "dilakukan", "sebagai", "protes", "terhadap", "hukum", "cambuk", "terhadap", "sejumlah", "tenaga", "kerja", "Indonesia", "di", "Negeri", "Jiran", "[", "baca", ":", "Demo", "Menentang", "Hukuman", "Cambuk", "buat", "TKI", "]", ".", "(", "MTA/Alam", "Burhanan", "dan", "Bambang", "Triono", ")", "."]], "clean_summary": [["Tiga", "pelaku", "pembakaran", "bendera", "Malaysia", "di", "Kedutaan", "Besar", "Malaysia", "diperiksa", "di", "Markas", "Polres", "Jakarta", "Selatan", "."], ["Seorang", "di", "antaranya", "Ketua", "Presidium", "Laskar", "Merah", "Putih", "Eddy", "Hartawan", "."]], "extractive_summary": [0, 1]}