{"id": 72368, "url": "https://www.liputan6.com/news/read/72368/kpu-menggodok-peraturan-pencalonan-capres", "clean_article": [["Liputan6", ".", "com", ",", "Jakarta", ":", "Komisi", "Pemilihan", "Umum", "tengah", "menggodok", "lima", "peraturan", "pencalonan", "presiden", "dan", "wakil", "presiden", "."], ["Antara", "lain", ",", "hanya", "partai", "politik", "atau", "gabungan", "parpol", "yang", "memiliki", "tiga", "persen", "kursi", "di", "DPR", "atau", "sekurang-kurangnya", "meraup", "lima", "persen", "suara", "yang", "dapat", "mengajukan", "pasangan", "capres", "dan", "wapres", "."], ["Demikian", "disampaikan", "anggota", "KPU", "Anas", "Urbaningrum", "di", "Jakarta", ",", "Senin", "(", "16/2", ")", "."], ["Peraturan", "lain", "membahas", "tentang", "kampanye", "dan", "tata", "cara", "penghitungan", "suara", "."], ["Diatur", "juga", ",", "setiap", "parpol", "atau", "gabungan", "parpol", "hanya", "boleh", "mencalonkan", "satu", "pasang", "capres", "dan", "wapres", "."], ["Pasangan", "yang", "sudah", "dicalonkan", "oleh", "parpol", "dan", "gabungan", "parpol", "tidak", "boleh", "dicalonkan", "lagi", "oleh", "parpol", "lain", "."], ["Anas", "menambahkan", ",", "pencalonan", "para", "capres", "dan", "kandidat", "wapres", "baru", "dimulai", "setelah", "KPU", "menetapkan", "anggota", "DPR", "resmi", "hasil", "pemilu", "."], ["Sedangkan", "waktu", "pengajuan", "calon", "hanya", "tujuh", "hari", ",", "mulai", "dari", "1-7", "Mei", "mendatang", ".", "(", "TNA/Dewvina", "Oktora", "dan", "Muhammad", "Guntur", ")", "."]], "clean_summary": [["Hanya", "parpol", "atau", "gabungan", "parpol", "yang", "memiliki", "tiga", "persen", "kursi", "di", "DPR", "atau", "sekurang-kurangnya", "memperoleh", "lima", "persen", "suara", "yang", "dapat", "mengajukan", "pasangan", "capres", "dan", "cawapres", "."]], "extractive_summary": [1, 3]}