{"id": 78041, "url": "https://www.liputan6.com/news/read/78041/gus-dur-yakin-kembali-berkuasa", "clean_article": [["Liputan6", ".", "com", ",", "Jakarta", ":", "Mantan", "Presiden", "Kiai", "Haji", "Abdurrahman", "Wahid", "merasa", "yakin", "peluang", "untuk", "berkuasa", "kembali", "cukup", "besar", "."], ["Terlebih", "lagi", ",", "kata", "dia", ",", "telah", "mendapat", "kabar", "dari", "sumbernya", "di", "Komisi", "Pemilihan", "Umum", "yang", "menyebutkan", "bakal", "lolos", "sebagai", "kandidat", "presiden", "dalam", "pemilu", "nanti", "."], ["Hal", "itu", "disampaikan", "Gus", "Dursapaan", "Abdurrahmandi", "Kantor", "Panitia", "Pengawas", "Pemilu", "di", "Jakarta", ",", "Kamis", "(", "13/5", ")", "."], ["Gus", "Dur", "mengaku", "akan", "serius", "memberantas", "korupsi", "jika", "kembali", "terpilih", "memimpin", "Indonesia", "."], ["Satu", "di", "antaranya", "dengan", "cara", "menaikkan", "gaji", "pegawai", "negeri", "hingga", "10", "kali", "lipat", "untuk", "mencegah", "birokrat", "mencuri", "uang", "negara", "."], ["Seperti", "halnya", "Gus", "Dur", ",", "Jenderal", "TNI", "Purnawirawan", "Wiranto", "juga", "mengaku", "akan", "memberantas", "korupsi", "apabila", "ia", "terpilih", "menjadi", "presiden", "."], ["Bahkan", ",", "dia", "setuju", "para", "koruptor", "dihukum", "mati", "saja", "."], ["Mantan", "Panglima", "ABRI", "ini", "juga", "mengaku", "telah", "mendapat", "dukungan", "dari", "partai", "untuk", "memenangkan", "pemilu", "[", "baca", ":", "Wiranto", "Mengaku", "Didukung", "PPNUI", "dan", "PPDK", "]", "."], ["Dukungan", "itu", "antara", "lain", "datang", "dari", "Partai", "Persatuan", "Demokrasi", "dan", "Kebangsaan", "pimpinan", "Ryas", "Rasyid", "dan", "Partai", "Persatuan", "Nahdlatul", "Ummah", "Indonesia", "."], ["Sedangkan", "dukungan", "dari", "Partai", "Karya", "Peduli", "Bangsa", "masih", "belum", "jelas", ".", "(", "AWD/Tim", "Liputan", "6", "SCTV", ")", "."]], "clean_summary": [["Ia", "mengaku", "peluangnya", "kembali", "memimpin", "negara", "terbuka", "setelah", "sumber", "di", "KPU", "menyebutkan", "dirinya", "bakal", "lolos", "menjadi", "capres", "."], ["Wiranto", "setuju", "para", "koruptor", "dihukum", "mati", "jika", "ia", "terpilih", "menjadi", "presiden", "."]], "extractive_summary": [3, 6]}