{"id": 95627, "url": "https://www.liputan6.com/news/read/95627/konfercab-pdip-jakpus-mendukung-megawati", "clean_article": [["Liputan6", ".", "com", ",", "Jakarta", ":", "Aksi", "dukung-mendukung", "untuk", "calon", "ketua", "umum", "Partai", "Demokrasi", "Indonesia", "dalam", "Kongres", "PDIP", "Bali", ",", "Maret", "mendatang", ",", "terus", "bergulir", "."], ["Salah", "satunya", "yang", "diputuskan", "dalam", "Konferensi", "Cabang", "PDIP", "Jakarta", "Pusat", ",", "Ahad", "(", "13/2", ")", "."], ["Dewan", "Pimpinan", "Cabang", "PDIP", "Jakpus", "memutuskan", "tetap", "mendukung", "Megawati", "Sukarnoputri", "sebagai", "ketua", "umum", "dalam", "kongres", "nanti", "."], ["\"", "Kalau", "untuk", "Mega", "[", "Megawati", "Sukarnoputri", "]", "sudah", "bulat", ",", "\"", "jelas", "Ketua", "DPC", "PDIP", "Jakpus", "Richard", "G", ".", "E", "."], ["Tulis", "."], ["Richard", "mengatakan", ",", "DPC", "PDIP", "Jakpus", "tidak", "terpengaruh", "dengan", "adanya", "gerakan", "pembaruan", "di", "tubuh", "partai", "[", "baca", ":", "Mantan", "Ketua", "PDIP", "Jateng", "Membentuk", "PDIP", "Pembaharuan", "]", "."], ["Konfercab", "digelar", "untuk", "konsolidasi", "semata", "dan", "mempersiapkan", "diri", "menghadapi", "Kongres", "Nasional", "di", "Bali", "."], ["Richard", "menambahkan", ",", "dalam", "kongres", "nanti", ",", "pihaknya", "akan", "memperjuangkan", "pembentukan", "majelis", "pertimbangan", "partai", "dan", "sistem", "pemilihan", "ketua", "umum", "satu", "paket", "dengan", "ketua", "harian", "dan", "sekretaris", "jenderal", "partai", ".", "(", "DEN/Fira", "Abdurachman", "dan", "Agus", "Ginanjar", ")", "."]], "clean_summary": [["Konferensi", "digelar", "untuk", "konsolidasi", "dan", "persiapan", "PDIP", "Cabang", "Jakpus", "menghadapi", "Kongres", "Nasional", "di", "Bali", "."], ["DPC", "PDIP", "Jakpus", "akan", "memperjuangkan", "sistem", "pemilihan", "ketua", "umum", "satu", "paket", "dengan", "ketua", "harian", "dan", "sekjen", "partai", "."]], "extractive_summary": [6, 7]}